surfacedev/__init__.py
surfacedev/client.py
surfacedev/config.py
surfacedev/default_config.py
surfacedev/session.py
surfacedev-0.1.0.dist-info/METADATA
surfacedev-0.1.0.dist-info/WHEEL
surfacedev-0.1.0.dist-info/RECORD
