Metadata-Version: 2.4
Name: surfacedev
Version: 0.1.0
Summary: Analytics SDK for tracking user events and sending them to Supabase
Author-email: Surface Dev <kasatkunanathan@gmail.com>
Requires-Python: >=3.11
Requires-Dist: python-dotenv>=1.0.0
Requires-Dist: supabase>=2.0.0
Provides-Extra: dev
Requires-Dist: black>=23.0.0; extra == 'dev'
Requires-Dist: pytest-asyncio>=0.23.0; extra == 'dev'
Requires-Dist: pytest>=8.0.0; extra == 'dev'
Requires-Dist: ruff>=0.1.0; extra == 'dev'
